<?xml version="1.0" encoding="UTF-8"?>
<ANNEX xmlns:xsi="http://www.w3.org/2001/XMLSchema-instance" xmlns:fmx="http://opoce" xsi:noNamespaceSchemaLocation="http://formex.publications.europa.eu/schema/formex-05.56-20160701.xd"><BIB.INSTANCE><DOCUMENT.REF FILE="L_2019083EN.01001801.doc.xml"><COLL>L</COLL><NO.OJ>083</NO.OJ><YEAR>2019</YEAR><LG.OJ>EN</LG.OJ><PAGE.FIRST>18</PAGE.FIRST><PAGE.SEQ>1</PAGE.SEQ><VOLUME.REF>01</VOLUME.REF></DOCUMENT.REF><DATE ISO="20190319">20190319</DATE><LG.DOC>EN</LG.DOC><NO.SEQ>0002.0001</NO.SEQ><PAGE.FIRST>36</PAGE.FIRST><PAGE.SEQ>1</PAGE.SEQ><PAGE.LAST>36</PAGE.LAST><PAGE.TOTAL>1</PAGE.TOTAL></BIB.INSTANCE><TITLE><TI><P>ANNEX I</P></TI></TITLE><CONTENTS><GR.SEQ LEVEL="1"><TITLE><TI><P><HT TYPE="BOLD">Repealed Regulation with list of the successive amendments thereto</HT></P></TI></TITLE><TBL COLS="2" NO.SEQ="0001"><CORPUS><ROW><CELL COL="1"><P>Council Regulation (EC) No 768/2005</P><P>(<REF.DOC.OJ COLL="L" DATE.PUB="20050521" NO.OJ="128" PAGE.FIRST="1">OJ L 128, 21.5.2005, p. 1</REF.DOC.OJ>).</P></CELL><CELL COL="2"><IE/></CELL></ROW><ROW><CELL COL="1"><P>Council Regulation (EC) No 1224/2009</P><P>(<REF.DOC.OJ COLL="L" DATE.PUB="20091122" NO.OJ="343" PAGE.FIRST="1">OJ L 343, 22.11.2009, p. 1</REF.DOC.OJ>).</P></CELL><CELL COL="2">Only Article 120</CELL></ROW><ROW><CELL COL="1"><P>Regulation (EU) 2016/1626 of the European Parliament and of the Council</P><P>(<REF.DOC.OJ COLL="L" DATE.PUB="20160916" NO.OJ="251" PAGE.FIRST="80">OJ L 251, 16.9.2016, p. 80</REF.DOC.OJ>).</P></CELL><CELL COL="2"><IE/></CELL></ROW></CORPUS></TBL></GR.SEQ></CONTENTS></ANNEX>